cons/__init__.py
cons/_version.py
cons/core.py
cons/unify.py
cons-0.4.2.dist-info/METADATA
cons-0.4.2.dist-info/WHEEL
cons-0.4.2.dist-info/top_level.txt
cons-0.4.2.dist-info/RECORD
